cognee_community_vector_adapter_milvus/__init__.py
cognee_community_vector_adapter_milvus/milvus_adapter.py
cognee_community_vector_adapter_milvus/register.py
cognee_community_vector_adapter_milvus-0.0.2.dist-info/METADATA
cognee_community_vector_adapter_milvus-0.0.2.dist-info/WHEEL
cognee_community_vector_adapter_milvus-0.0.2.dist-info/RECORD
