Metadata-Version: 2.3
Name: cognee-community-vector-adapter-milvus
Version: 0.0.2
Summary: Milvus vector database adapter for cognee
Requires-Python: >=3.11,<=3.13
Classifier: Programming Language :: Python :: 3
Classifier: Programming Language :: Python :: 3.11
Classifier: Programming Language :: Python :: 3.12
Classifier: Programming Language :: Python :: 3.13
Provides-Extra: dev
Requires-Dist: cognee (>=0.2.4)
Requires-Dist: milvus-lite (>=2.4.0) ; sys_platform != "win32"
Requires-Dist: mypy (>=1.10,<2) ; extra == "dev"
Requires-Dist: pymilvus (>=2.5.0,<3)
